plette/__init__.py
plette/__main__.py
plette/lockfiles.py
plette/pipfiles.py
plette/models/__init__.py
plette/models/base.py
plette/models/hashes.py
plette/models/packages.py
plette/models/scripts.py
plette/models/sections.py
plette/models/sources.py
plette-2.1.0.dist-info/LICENSE
plette-2.1.0.dist-info/METADATA
plette-2.1.0.dist-info/WHEEL
plette-2.1.0.dist-info/top_level.txt
plette-2.1.0.dist-info/zip-safe
plette-2.1.0.dist-info/RECORD
