Metadata-Version: 2.1
Name: plette
Version: 2.1.0
Summary: Structured Pipfile and Pipfile.lock models.
Author-email: Tzu-ping Chung <uranusjr@gmail.com>
License: ISC License
Project-URL: Homepage, https://github.com/sarugaku/plette
Classifier: Development Status :: 1 - Planning
Classifier: License :: OSI Approved :: ISC License (ISCL)
Classifier: Operating System :: OS Independent
Classifier: Programming Language :: Python :: 3
Classifier: Programming Language :: Python :: 3.7
Classifier: Programming Language :: Python :: 3.8
Classifier: Programming Language :: Python :: 3.9
Classifier: Programming Language :: Python :: 3.10
Classifier: Topic :: Software Development :: Libraries :: Python Modules
Requires-Python: >=3.7
License-File: LICENSE
Requires-Dist: tomlkit
Provides-Extra: tests
Requires-Dist: pytest; extra == "tests"
Requires-Dist: pytest-cov; extra == "tests"
Requires-Dist: pytest-xdist; extra == "tests"
Provides-Extra: validation
Requires-Dist: cerberus; extra == "validation"
